cirrus_lib/__init__.py
cirrus_lib/configs.py
cirrus_lib/components/__init__.py
cirrus_lib/components/aws/__init__.py
cirrus_lib/components/aws/vpc.py
stratos_lib-0.1.0.dist-info/METADATA
stratos_lib-0.1.0.dist-info/WHEEL
stratos_lib-0.1.0.dist-info/RECORD
